eurekatrees/__init__.py
eurekatrees/eurekatrees.py
eurekatrees/templates/home_template.jinja2
eurekatrees/templates/tree_template.jinja2
eurekatrees-0.3.dist-info/METADATA
eurekatrees-0.3.dist-info/RECORD
eurekatrees-0.3.dist-info/WHEEL
eurekatrees-0.3.dist-info/entry_points.txt
eurekatrees-0.3.dist-info/top_level.txt
