Metadata-Version: 2.1
Name: eurekatrees
Version: 0.3
Summary: Spark MLLib debug string converter to visualization
Home-page: http://github.com/ChuckWoodraska/EurekaTrees
Author: Chuck Woodraska
Author-email: chuck.woodraska@gmail.com
License: MIT
Platform: UNKNOWN
Requires-Dist: jinja2
